Workbook

Sheet 埋点数据
A1: 时间 | B1: event_type | C1: query | D1: desensitized_query | E1: intent | F1: confidence | G1: reason | H1: risk_type | I1: risk_reason | J1: conversation_id | K1: dialogue_count | L1: payload_json | M1: transfer_json | N1: badcase_json
A2: 46216.724 | B2: intent_classify | C2: T恤是什么材质的？ | D2: T恤是什么材质的？ | E2: 售前咨询 | F2: 0.98 | G2: 询问商品材质，属于购买前常见问题 | H2: 无 | I2: 正常咨询 | J2: fcf8d425-6db6-405e-baaf-2cf3735b295f | K2: 1
A3: 46216.724 | B3: intent_classify | C3: T恤是什么材质的？ | D3: T恤是什么材质的？ | E3: 售前咨询 | L3: {"event": "knowledge_search
A4: 46216.724 | B4: intent_classify | C4: T恤是什么材质的？ | D4: T恤是什么材质的？ | E4: 售前咨询 | L4: {"event": "answer_generate
A5: 46223.479 | B5: intent_classify | C5: 这件T恤是什么材质的 | D5: 这件T恤是什么材质的 | E5: 售前咨询 | F5: 0.98 | G5: 询问商品材质，属于购买前的问题 | H5: 无 | I5: 正常问题 | J5: 03255551-0fe4-4a96-9c25-cb0d8c6fe99a | K5: 1
A6: 46223.479 | B6: intent_classify | C6: 这件T恤是什么材质的 | D6: 这件T恤是什么材质的 | E6: 售前咨询 | L6: {"event": "knowledge_search
A7: 46223.479 | B7: intent_classify | C7: 这件T恤是什么材质的 | D7: 这件T恤是什么材质的 | E7: 售前咨询 | L7: {"event": "answer_generate
A8: 46223.479 | B8: intent_classify | C8: 有优惠吗 | D8: 有优惠吗 | E8: 售前咨询 | F8: 0.95 | G8: 询问优惠信息 | H8: 无 | I8: 正常咨询 | J8: 165c548a-134a-4eb4-aa72-79f78ecb4afa | K8: 1
A9: 46223.479 | B9: intent_classify | C9: 有优惠吗 | D9: 有优惠吗 | E9: 售前咨询 | L9: {"event": "knowledge_search
A10: 46223.479 | B10: intent_classify | C10: 有优惠吗 | D10: 有优惠吗 | E10: 售前咨询 | L10: {"event": "answer_generate
A11: 46223.479 | B11: intent_classify | C11: 我身高170体重120穿什么码 | D11: 我身高170体重120穿什么码 | E11: 售前咨询 | F11: 0.95 | G11: 询问适合的尺码，属于购买前商品信息咨询 | H11: 无 | I11: 正常尺码咨询 | J11: f9f44473-d48a-4947-ae2e-e7e3b6e3284d | K11: 1
A12: 46223.479 | B12: intent_classify | C12: 我身高170体重120穿什么码 | D12: 我身高170体重120穿什么码 | E12: 售前咨询 | L12: {"event": "knowledge_search
A13: 46223.479 | B13: intent_classify | C13: 我身高170体重120穿什么码 | D13: 我身高170体重120穿什么码 | E13: 售前咨询 | L13: {"event": "answer_generate
A14: 46223.479 | B14: intent_classify | C14: 白色会不会透 | D14: 白色会不会透 | E14: 售前咨询 | F14: 0.95 | G14: 询问商品颜色特性（白色是否透明），属于购买前商品信息咨询 | H14: 无 | I14: 正常问答 | J14: cdcdfe0a-64fe-429c-995e-26eaef612110 | K14: 1
A15: 46223.48 | B15: intent_classify | C15: 白色会不会透 | D15: 白色会不会透 | E15: 售前咨询 | L15: {"event": "knowledge_search
A16: 46223.48 | B16: intent_classify | C16: 白色会不会透 | D16: 白色会不会透 | E16: 售前咨询 | L16: {"event": "answer_generate
A17: 46223.48 | B17: intent_classify | C17: 这件T恤是什么材质的 | D17: 这件T恤是什么材质的 | E17: 售前咨询 | F17: 0.95 | G17: 询问商品材质 | H17: 无 | I17: 正常询问 | J17: ba0ac03b-9bf0-4124-ac26-37baf13bb6c5 | K17: 1
A18: 46223.48 | B18: intent_classify | C18: 牛仔裤有弹力吗 | D18: 牛仔裤有弹力吗 | E18: 售前咨询 | F18: 0.95 | G18: 询问商品功能（弹力） | H18: 无 | I18: 正常商品咨询 | J18: 5052743c-2e87-4667-b72c-bbd977dbf746 | K18: 1
A19: 46223.48 | B19: intent_classify | C19: 这件T恤是什么材质的 | D19: 这件T恤是什么材质的 | E19: 售前咨询 | L19: {"event": "knowledge_search
A20: 46223.48 | B20: intent_classify | C20: 牛仔裤有弹力吗 | D20: 牛仔裤有弹力吗 | E20: 售前咨询 | L20: {"event": "knowledge_search
A21: 46223.48 | B21: intent_classify | C21: 这件T恤是什么材质的 | D21: 这件T恤是什么材质的 | E21: 售前咨询 | L21: {"event": "answer_generate
A22: 46223.48 | B22: intent_classify | C22: 牛仔裤有弹力吗 | D22: 牛仔裤有弹力吗 | E22: 售前咨询 | L22: {"event": "answer_generate
A23: 46223.48 | B23: intent_classify | C23: 有优惠吗 | D23: 有优惠吗 | E23: 售前咨询 | F23: 0.95 | G23: 询问商品优惠信息 | H23: 无 | I23: 正常询问优惠 | J23: b0d3165b-8ba0-49ea-b4e0-afe42de8c241 | K23: 1
A24: 46223.48 | B24: intent_classify | C24: 有优惠吗 | D24: 有优惠吗 | E24: 售前咨询 | L24: {"event": "knowledge_search
A25: 46223.48 | B25: intent_classify | C25: 这个和那个有什么区别 | D25: 这个和那个有什么区别 | E25: 售前咨询 | F25: 0.95 | G25: 询问商品区别，属购买前信息咨询 | H25: 无 | I25: 普通询问差异 | J25: 5202b348-397c-49f7-929c-aaf5001769c5 | K25: 1
A26: 46223.48 | B26: intent_classify | C26: 有优惠吗 | D26: 有优惠吗 | E26: 售前咨询 | L26: {"event": "answer_generate
A27: 46223.48 | B27: intent_classify | C27: 这个和那个有什么区别 | D27: 这个和那个有什么区别 | E27: 售前咨询 | L27: {"event": "knowledge_search
A28: 46223.48 | B28: intent_classify | C28: 现在下单什么时候能到 | D28: 现在下单什么时候能到 | E28: 售前咨询 | F28: 0.98 | G28: 询问下单后的到货时间，属于购买前物流时效咨询 | H28: 无 | I28: 正常咨询物流时间 | J28: e75c2a8e-3f76-45ca-8189-ab3155a911eb | K28: 1
A29: 46223.48 | B29: intent_classify | C29: 现在下单什么时候能到 | D29: 现在下单什么时候能到 | E29: 售前咨询 | L29: {"event": "knowledge_search
A30: 46223.48 | B30: intent_classify | C30: 现在下单什么时候能到 | D30: 现在下单什么时候能到 | E30: 售前咨询 | L30: {"event": "answer_generate
A31: 46223.48 | B31: intent_classify | C31: 能便宜点吗 | D31: 能便宜点吗 | E31: 售前咨询 | F31: 0.99 | G31: 询问价格优惠，属于购买前咨询 | H31: 无 | I31: 正常砍价 | J31: 70b99fe9-1984-4d8c-9b90-8697b0ef08b9 | K31: 1
A32: 46223.48 | B32: intent_classify | C32: 能便宜点吗 | D32: 能便宜点吗 | E32: 售前咨询 | L32: {"event": "knowledge_search
A33: 46223.481 | B33: intent_classify | C33: 羽绒服适合什么温度穿 | D33: 羽绒服适合什么温度穿 | E33: 售前咨询 | F33: 0.95 | G33: 询问商品使用场景 | H33: 无 | I33: 正常商品咨询 | J33: e1272178-b1d8-40fb-93c3-30fe51a542f9 | K33: 1
A34: 46223.481 | B34: intent_classify | C34: 这件T恤是什么材质的 | D34: 这件T恤是什么材质的 | E34: 售前咨询 | F34: 0.98 | G34: 询问商品材质，属于购买前商品信息咨询 | H34: 无 | I34: 正常商品咨询 | J34: 029553eb-c3d6-4329-a135-a7d6b342e76c | K34: 1
A35: 46223.481 | B35: intent_classify | C35: 羽绒服适合什么温度穿 | D35: 羽绒服适合什么温度穿 | E35: 售前咨询 | L35: {"event": "knowledge_search
A36: 46223.481 | B36: intent_classify | C36: 这件T恤是什么材质的 | D36: 这件T恤是什么材质的 | E36: 售前咨询 | L36: {"event": "knowledge_search
A37: 46223.481 | B37: intent_classify | C37: 羽绒服适合什么温度穿 | D37: 羽绒服适合什么温度穿 | E37: 售前咨询 | L37: {"event": "answer_generate
A38: 46223.481 | B38: intent_classify | C38: 这件T恤是什么材质的 | D38: 这件T恤是什么材质的 | E38: 售前咨询 | L38: {"event": "answer_generate
A39: 46223.481 | B39: intent_classify | C39: 支持花呗吗 | D39: 支持花呗吗 | E39: 售前咨询 | F39: 0.95 | G39: 询问支付方式，属于购买前常见问题 | H39: 无 | I39: 普通询问，无风险 | J39: c209ef1e-8ddd-4a8c-865b-b77f61328a54 | K39: 1
A40: 46223.481 | B40: intent_classify | C40: 有优惠吗 | D40: 有优惠吗 | E40: 售前咨询 | F40: 0.99 | G40: 询问优惠，属于购买前的信息咨询 | H40: 无 | I40: 正常询问 | J40: d76385e1-ff08-401d-99e0-fa56854b0356 | K40: 1
A41: 46223.481 | B41: intent_classify | C41: 支持花呗吗 | D41: 支持花呗吗 | E41: 售前咨询 | L41: {"event": "knowledge_search
A42: 46223.481 | B42: intent_classify | C42: 有优惠吗 | D42: 有优惠吗 | E42: 售前咨询 | L42: {"event": "knowledge_search
A43: 46223.481 | B43: intent_classify | C43: 支持花呗吗 | D43: 支持花呗吗 | E43: 售前咨询 | L43: {"event": "answer_generate
A44: 46223.481 | B44: intent_classify | C44: 有优惠吗 | D44: 有优惠吗 | E44: 售前咨询 | L44: {"event": "answer_generate
A45: 46223.481 | B45: intent_classify | C45: 有没有其他颜色 | D45: 有没有其他颜色 | E45: 售前咨询 | F45: 0.99 | G45: 询问商品颜色 | H45: 无 | I45: 无用户输入 | J45: 710f4788-f7a4-4d2a-9d96-280799501d98 | K45: 1
A46: 46223.481 | B46: intent_classify | C46: 我身高170体重120穿什么码 | D46: 我身高170体重120穿什么码 | E46: 售前咨询 | F46: 0.99 | G46: 询问身高体重对应尺码，属于购买前的商品信息咨询 | H46: 无 | I46: 正常尺寸咨询 | J46: 6d3cca7a-da47-4c4c-bfcd-11b18f1fb159 | K46: 1
A47: 46223.481 | B47: intent_classify | C47: 有没有其他颜色 | D47: 有没有其他颜色 | E47: 售前咨询 | L47: {"event": "knowledge_search
A48: 46223.481 | B48: intent_classify | C48: 我身高170体重120穿什么码 | D48: 我身高170体重120穿什么码 | E48: 售前咨询 | L48: {"event": "knowledge_search
A49: 46223.481 | B49: intent_classify | C49: 有没有其他颜色 | D49: 有没有其他颜色 | E49: 售前咨询 | L49: {"event": "answer_generate
A50: 46223.481 | B50: intent_classify | C50: 我身高170体重120穿什么码 | D50: 我身高170体重120穿什么码 | E50: 售前咨询 | L50: {"event": "answer_generate
A51: 46223.481 | B51: intent_classify | C51: 这个洗了会缩水吗 | D51: 这个洗了会缩水吗 | E51: 售前咨询 | F51: 0.98 | G51: 询问商品洗涤后是否缩水，属于购买前商品信息咨询 | H51: 无 | I51: 正常产品咨询 | J51: 75929c8d-12ab-4575-bb8f-5a1f8d5cb6c2 | K51: 1
A52: 46223.481 | B52: intent_classify | C52: 白色会不会透 | D52: 白色会不会透 | E52: 售前咨询 | F52: 0.95 | G52: 询问商品颜色属性 | H52: 无 | I52: 普通产品咨询 | J52: 19138ae0-fc0d-4816-96c8-5c8d9aa40c9c | K52: 1
A53: 46223.481 | B53: intent_classify | C53: 这个洗了会缩水吗 | D53: 这个洗了会缩水吗 | E53: 售前咨询 | L53: {"event": "knowledge_search
A54: 46223.481 | B54: intent_classify | C54: 白色会不会透 | D54: 白色会不会透 | E54: 售前咨询 | L54: {"event": "knowledge_search
A55: 46223.481 | B55: intent_classify | C55: 这个洗了会缩水吗 | D55: 这个洗了会缩水吗 | E55: 售前咨询 | L55: {"event": "answer_generate
A56: 46223.481 | B56: intent_classify | C56: 白色会不会透 | D56: 白色会不会透 | E56: 售前咨询 | L56: {"event": "answer_generate
A57: 46223.482 | B57: intent_classify | C57: 牛仔裤有弹力吗 | D57: 牛仔裤有弹力吗 | E57: 售前咨询 | F57: 0.99 | G57: 询问商品材质特性 | H57: 无 | I57: 正常商品咨询 | J57: b05e8af7-c6a1-4d6c-87ef-d79d69b6608d | K57: 1
A58: 46223.482 | B58: intent_classify | C58: 发什么快递 | D58: 发什么快递 | E58: 售前咨询 | F58: 0.9 | G58: 用户询问发货快递，属于购买前常见询问配送方式的售前问题 | H58: 无 | I58: 无风险 | J58: e7e425ec-7928-44b9-bbc2-16ceee7ad7eb | K58: 1
A59: 46223.482 | B59: intent_classify | C59: 牛仔裤有弹力吗 | D59: 牛仔裤有弹力吗 | E59: 售前咨询 | L59: {"event": "knowledge_search
A60: 46223.482 | B60: intent_classify | C60: 发什么快递 | D60: 发什么快递 | E60: 售前咨询 | L60: {"event": "knowledge_search
A61: 46223.482 | B61: intent_classify | C61: 牛仔裤有弹力吗 | D61: 牛仔裤有弹力吗 | E61: 售前咨询 | L61: {"event": "answer_generate
A62: 46223.482 | B62: intent_classify | C62: 发什么快递 | D62: 发什么快递 | E62: 售前咨询 | L62: {"event": "answer_generate
A63: 46223.482 | B63: intent_classify | C63: 这个和那个有什么区别 | D63: 这个和那个有什么区别 | E63: 售前咨询 | F63: 0.95 | G63: 询问商品之间的区别，属于购买前了解商品信息的售前咨询 | H63: 无 | I63: 正常提问 | J63: cc4d8a07-5ee7-4072-a34e-7f2503eca20a | K63: 1
A64: 46223.482 | B64: intent_classify | C64: 能开发票吗 | D64: 能开发票吗 | E64: 售前咨询 | F64: 0.95 | G64: 询问是否支持开发票，属于购买前常见商品服务咨询 | H64: 无 | I64: 正常查询 | J64: 03874c5b-2928-4e62-aa9e-546b4cf3ee65 | K64: 1
A65: 46223.482 | B65: intent_classify | C65: 这个和那个有什么区别 | D65: 这个和那个有什么区别 | E65: 售前咨询 | L65: {"event": "knowledge_search
A66: 46223.482 | B66: intent_classify | C66: 能开发票吗 | D66: 能开发票吗 | E66: 售前咨询 | L66: {"event": "knowledge_search
A67: 46223.482 | B67: intent_classify | C67: 能开发票吗 | D67: 能开发票吗 | E67: 售前咨询 | L67: {"event": "answer_generate
A68: 46223.482 | B68: intent_classify | C68: 现在下单什么时候能到 | D68: 现在下单什么时候能到 | E68: 售前咨询 | F68: 0.95 | G68: 询问下单后的配送时间，属于购买前常规咨询 | H68: 无 | I68: 正常咨询物流时效 | J68: 2001539f-eddd-441e-a823-e7ec89f48c32 | K68: 1
A69: 46223.482 | B69: intent_classify | C69: 现在下单什么时候能到 | D69: 现在下单什么时候能到 | E69: 售前咨询 | L69: {"event": "knowledge_search
A70: 46223.482 | B70: intent_classify | C70: 双十一有活动吗 | D70: 双十一有活动吗 | E70: 售前咨询 | F70: 0.98 | G70: 询问双十一促销活动，属于购买前咨询 | H70: 无 | I70: 正常询问 | J70: 294c12e2-6bc9-41b1-8486-45e510782b26 | K70: 1
A71: 46223.482 | B71: intent_classify | C71: 双十一有活动吗 | D71: 双十一有活动吗 | E71: 售前咨询 | L71: {"event": "knowledge_search
A72: 46223.482 | B72: intent_classify | C72: 现在下单什么时候能到 | D72: 现在下单什么时候能到 | E72: 售前咨询 | L72: {"event": "answer_generate
A73: 46223.482 | B73: intent_classify | C73: 牛仔裤会掉色吗 | D73: 牛仔裤会掉色吗 | E73: 售前咨询 | F73: 0.98 | G73: 询问商品特性，无负面情绪 | H73: 无 | I73: 正常咨询 | J73: 0823dde7-b6af-45ba-a412-a228784b2173 | K73: 1
A74: 46223.482 | B74: intent_classify | C74: 能便宜点吗 | D74: 能便宜点吗 | E74: 售前咨询 | F74: 0.95 | G74: 询问价格优惠，属于购买前的价格协商问题 | H74: 无 | I74: 正常询问，无风险 | J74: 8cd6ddf1-b541-492f-8479-a49932741774 | K74: 1
A75: 46223.482 | B75: intent_classify | C75: 牛仔裤会掉色吗 | D75: 牛仔裤会掉色吗 | E75: 售前咨询 | L75: {"event": "knowledge_search
A76: 46223.482 | B76: intent_classify | C76: 牛仔裤会掉色吗 | D76: 牛仔裤会掉色吗 | E76: 售前咨询 | L76: {"event": "answer_generate
A77: 46223.482 | B77: intent_classify | C77: 能便宜点吗 | D77: 能便宜点吗 | E77: 售前咨询 | L77: {"event": "knowledge_search
A78: 46223.482 | B78: intent_classify | C78: 小个子穿会太长吗 | D78: 小个子穿会太长吗 | E78: 售前咨询 | F78: 0.98 | G78: 询问商品尺码长度是否适合特定身高 | H78: 无 | I78: 正常询问尺寸 | J78: d3bd6950-d77f-4ff0-8c13-8f188e53b749 | K78: 1
A79: 46223.482 | B79: intent_classify | C79: 羽绒服适合什么温度穿 | D79: 羽绒服适合什么温度穿 | E79: 售前咨询 | F79: 0.98 | G79: 询问羽绒服的适用温度，属于售前商品功能咨询 | H79: 无 | I79: 正常服装咨询 | J79: 7612088b-e408-4a79-ad3c-32451e8c0c79 | K79: 1
A80: 46223.482 | B80: intent_classify | C80: 小个子穿会太长吗 | D80: 小个子穿会太长吗 | E80: 售前咨询 | L80: {"event": "knowledge_search
A81: 46223.482 | B81: intent_classify | C81: 羽绒服适合什么温度穿 | D81: 羽绒服适合什么温度穿 | E81: 售前咨询 | L81: {"event": "knowledge_search
A82: 46223.483 | B82: intent_classify | C82: 羽绒服适合什么温度穿 | D82: 羽绒服适合什么温度穿 | E82: 售前咨询 | L82: {"event": "answer_generate
A83: 46223.483 | B83: intent_classify | C83: 羽绒服能机洗吗 | D83: 羽绒服能机洗吗 | E83: 售前咨询 | F83: 0.98 | G83: 询问羽绒服机洗可行性，属商品使用咨询 | H83: 无 | I83: 正常商品咨询 | J83: 9f899879-4a8f-4af6-bf09-09e01c77ede9 | K83: 1
A84: 46223.483 | B84: intent_classify | C84: 羽绒服能机洗吗 | D84: 羽绒服能机洗吗 | E84: 售前咨询 | L84: {"event": "knowledge_search
A85: 46223.483 | B85: intent_classify | C85: 羽绒服能机洗吗 | D85: 羽绒服能机洗吗 | E85: 售前咨询 | L85: {"event": "answer_generate
A86: 46223.483 | B86: intent_classify | C86: 支持花呗吗 | D86: 支持花呗吗 | E86: 售前咨询 | F86: 0.95 | G86: 询问支付方式 | H86: 无 | I86: 正常咨询支付方式 | J86: 1324af01-c4a1-44f6-b729-0aaa7743a8a1 | K86: 1
A87: 46223.483 | B87: intent_classify | C87: 支持花呗吗 | D87: 支持花呗吗 | E87: 售前咨询 | L87: {"event": "knowledge_search
A88: 46223.483 | B88: intent_classify | C88: 有没有套装 | D88: 有没有套装 | E88: 售前咨询 | F88: 0.98 | G88: 询问是否有套装商品，属于购买前的商品咨询 | H88: 无 | I88: 输入为空 | J88: 4a99c022-33fe-4dd3-a4f6-285dc273af01 | K88: 1
A89: 46223.483 | B89: intent_classify | C89: 支持花呗吗 | D89: 支持花呗吗 | E89: 售前咨询 | L89: {"event": "answer_generate
A90: 46223.483 | B90: intent_classify | C90: 有没有套装 | D90: 有没有套装 | E90: 售前咨询 | L90: {"event": "knowledge_search
A91: 46223.483 | B91: intent_classify | C91: 有没有其他颜色 | D91: 有没有其他颜色 | E91: 售前咨询 | F91: 0.98 | G91: 询问商品颜色选项 | H91: 无 | I91: 无用户输入 | J91: c18ff240-72c9-457a-9e02-08fa272863ed | K91: 1
A92: 46223.483 | B92: intent_classify | C92: 有没有套装 | D92: 有没有套装 | E92: 售前咨询 | L92: {"event": "answer_generate
A93: 46223.483 | B93: intent_classify | C93: 有没有其他颜色 | D93: 有没有其他颜色 | E93: 售前咨询 | L93: {"event": "knowledge_search
A94: 46223.483 | B94: intent_classify | C94: 这是正品吗 | D94: 这是正品吗 | E94: 售前咨询 | F94: 0.98 | G94: 用户询问商品是否为正品，属于购买前的商品信息咨询 | H94: 无 | I94: 正常询问 | J94: 2f41d665-8fe6-4e6a-b7df-2a01edd03933 | K94: 1
A95: 46223.483 | B95: intent_classify | C95: 有没有其他颜色 | D95: 有没有其他颜色 | E95: 售前咨询 | L95: {"event": "answer_generate
A96: 46223.483 | B96: intent_classify | C96: 这是正品吗 | D96: 这是正品吗 | E96: 售前咨询 | L96: {"event": "knowledge_search
A97: 46223.483 | B97: intent_classify | C97: 这个洗了会缩水吗 | D97: 这个洗了会缩水吗 | E97: 售前咨询 | F97: 0.98 | G97: 询问商品洗涤后是否会缩水，属于购买前了解商品属性 | H97: 无 | I97: 正常咨询 | J97: aa9e9b3b-4674-4370-989d-90f522dbd172 | K97: 1
A98: 46223.483 | B98: intent_classify | C98: 我的订单发货了吗 | D98: 我的订单发货了吗 | E98: 订单查询 | F98: 0.99 | G98: 用户询问订单发货状态，属于订单查询 | H98: 无 | I98: 正常订单查询 | J98: c95346ed-d2e7-4d07-9cde-8daf8a660d5f | K98: 1
A99: 46223.483 | B99: intent_classify | C99: 这个洗了会缩水吗 | D99: 这个洗了会缩水吗 | E99: 售前咨询 | L99: {"event": "knowledge_search
A100: 46223.483 | B100: intent_classify | C100: 我的订单发货了吗 | D100: 我的订单发货了吗 | E100: 订单查询 | L100: {"event": "knowledge_search
...

Sheet 意图分析
A1: 意图 | B1: 次数 | C1: 占比
A2: {=UNIQUE('埋点数据'!E:E)} -> intent | B2: =COUNTIF('埋点数据'!E:E,A2) -> 1 | C2: =IF(B2>0,B2/SUM(B:B),0) -> 0.002617801
A3: 售前咨询 | B3: =COUNTIF('埋点数据'!E:E,A3) -> 145 | C3: =IF(B3>0,B3/SUM(B:B),0) -> 0.37958115
A4: 订单查询 | B4: =COUNTIF('埋点数据'!E:E,A4) -> 82 | C4: =IF(B4>0,B4/SUM(B:B),0) -> 0.21465969
A5: 其他 | B5: =COUNTIF('埋点数据'!E:E,A5) -> 21 | C5: =IF(B5>0,B5/SUM(B:B),0) -> 0.054973822
A6: 退换货 | B6: =COUNTIF('埋点数据'!E:E,A6) -> 38 | C6: =IF(B6>0,B6/SUM(B:B),0) -> 0.09947644
A7: 投诉 | B7: =COUNTIF('埋点数据'!E:E,A7) -> 34 | C7: =IF(B7>0,B7/SUM(B:B),0) -> 0.089005236
A8: 闲聊 | B8: =COUNTIF('埋点数据'!E:E,A8) -> 61 | C8: =IF(B8>0,B8/SUM(B:B),0) -> 0.15968586

Sheet 每日统计
A1: =IFERROR(__xludf.DUMMYFUNCTION("QUERY(ARRAYFORMULA({TEXT('埋点数据'!A2:A1000,""yyyy-mm-dd""),'埋点数据'!B2:B1000}),""select Col1,count(Col1) where Col1 is not null and Col1 <> '1899-12-30' group by Col1 label Col1'日期',count(Col1)'对话数'"",0)"),"日期") -> 日期 | B1: =IFERROR(__xludf.DUMMYFUNCTION("""COMPUTED_VALUE"""),"对话数") -> 对话数
A2: =IFERROR(__xludf.DUMMYFUNCTION("""COMPUTED_VALUE"""),"2026-07-13") -> 2026-07-13 | B2: =IFERROR(__xludf.DUMMYFUNCTION("""COMPUTED_VALUE"""),3.0) -> 3
A3: =IFERROR(__xludf.DUMMYFUNCTION("""COMPUTED_VALUE"""),"2026-07-20") -> 2026-07-20 | B3: =IFERROR(__xludf.DUMMYFUNCTION("""COMPUTED_VALUE"""),378.0) -> 378

Sheet 监控看板
A1: 总对话数 | B1: =COUNTA('埋点数据'!A:A)-1 -> 381
A2: 售前咨询数 | B2: =COUNTIF('埋点数据'!E:E, "售前咨询") -> 145
A3: 退换货数 | B3: =COUNTIF('埋点数据'!E:E, "退换货") -> 38
A4: 投诉数 | B4: =COUNTIF('埋点数据'!E:E, "投诉") -> 34
A5: 转人工数 | B5: =COUNTIF('埋点数据'!E:E, "投诉")+COUNTIF('埋点数据'!E:E, "其他") -> 55
A6: 风控拦截数 | B6: =COUNTIFS('埋点数据'!H:H, "<>", '埋点数据'!H:H, "<>无") -> 1
A7: 有知识回答率 | B7: =IFERROR(COUNTIF('埋点数据'!L:L, "*answer_generate*")/COUNTIF('埋点数据'!L:L, "*knowledge_search*"), 0) -> 0.63247863
